pyswirl/.DS_Store
pyswirl/__init__.py
pyswirl/pyswirl.py
pyswirl-0.0.1.dist-info/METADATA
pyswirl-0.0.1.dist-info/WHEEL
pyswirl-0.0.1.dist-info/licenses/LICENSE
pyswirl-0.0.1.dist-info/RECORD
