Metadata-Version: 2.1
Name: pyswirl
Version: 0.0.1
Summary: A simple package to draw swirl shapes
Project-URL: Homepage, https://github.com/sairam-penjarla/pyswirl/
Project-URL: Bug Tracker, https://github.com/sairam-penjarla/pyswirl/issues
Author-email: Sai Ram Penjarla <psairam9301@gmail.com>
License-File: LICENSE
Classifier: License :: OSI Approved :: MIT License
Classifier: Operating System :: OS Independent
Classifier: Programming Language :: Python :: 3
Requires-Python: >=3.7
